<?xml version="1.0" encoding="UTF-8" ?>

<!DOCTYPE struts PUBLIC "-//Apache Software Foundation//DTD Struts Configuration 2.1.7//EN" "http://struts.apache.org/dtds/struts-2.1.7.dtd">

<struts>
	<package name="public" extends="struts-default">
		<result-types>
			<result-type name="json" class="org.apache.struts2.json.JSONResult"/>
			<result-type name="freemarker" class="org.mspring.mlog.web.result.FreemarkerResult" />
			<result-type name="theme" class="org.mspring.mlog.web.result.ThemeResult" />
		</result-types>
	
        
		<!-- 拦截器 -->
		<interceptors>
			<!-- struts json plugin -->
			<interceptor name="json" class="org.apache.struts2.json.JSONInterceptor"/>
			
			<!-- <interceptor name="exception" class="org.mspring.platform.web.xwork.interceptor.ExceptionInterceptor" /> -->
			<interceptor name="autowiring" class="com.opensymphony.xwork2.spring.interceptor.ActionAutowiringInterceptor"/>
			<interceptor name="queryParameter" class="org.mspring.platform.web.xwork.interceptor.QueryParameterInterceptor" />
			
			<interceptor-stack name="defaultStack">
				<interceptor-ref name="queryParameter" />
				<interceptor-ref name="autowiring" />
				<interceptor-ref name="alias"/>
                <interceptor-ref name="servletConfig"/>
                <interceptor-ref name="chain"/>
                <interceptor-ref name="params"/>
                <interceptor-ref name="json" />
				<interceptor-ref name="exception"/>
				<interceptor-ref name="alias"/>
                <interceptor-ref name="servletConfig"/>
                <interceptor-ref name="i18n"/>
                <interceptor-ref name="prepare"/>
                <interceptor-ref name="chain"/>
                <interceptor-ref name="debugging"/>
                <interceptor-ref name="scopedModelDriven"/>
                <interceptor-ref name="modelDriven"/>
                <interceptor-ref name="fileUpload"/>
                <interceptor-ref name="checkbox"/>
                <interceptor-ref name="multiselect"/>
                <interceptor-ref name="staticParams"/>
                <interceptor-ref name="actionMappingParams"/>
                <interceptor-ref name="params">
                  <param name="excludeParams">dojo\..*,^struts\..*</param>
                </interceptor-ref>
                <interceptor-ref name="conversionError"/>
                <interceptor-ref name="validation">
                    <param name="excludeMethods">input,back,cancel,browse</param>
                </interceptor-ref>
                <interceptor-ref name="workflow">
                    <param name="excludeMethods">input,back,cancel,browse</param>
                </interceptor-ref>
			</interceptor-stack>
			
			<interceptor-stack name="fileUploadStack">
				<interceptor-ref name="autowiring" />
				<interceptor-ref name="queryParameter" />
				<interceptor-ref name="exception" />
				<interceptor-ref name="alias"/>
                <interceptor-ref name="servletConfig"/>
                <interceptor-ref name="chain"/>
                <interceptor-ref name="params"/>
                <interceptor-ref name="fileUpload"/>
			</interceptor-stack>
		</interceptors>
		<default-interceptor-ref name="defaultStack" />
		
		<global-results>
            <result name="exception" type="dispatcher">/common/error.jsp</result>
            <result name="prompt" type="dispatcher">/admin/common/prompt.jsp</result>
        </global-results>
	</package>
</struts>
